fgdb_to_gpkg/__init__.py
fgdb_to_gpkg/fgdb_to_gpkg.py
fgdb_to_gpkg-0.4.5.dist-info/METADATA
fgdb_to_gpkg-0.4.5.dist-info/WHEEL
fgdb_to_gpkg-0.4.5.dist-info/entry_points.txt
fgdb_to_gpkg-0.4.5.dist-info/licenses/LICENSE
fgdb_to_gpkg-0.4.5.dist-info/RECORD
