Metadata-Version: 2.4
Name: fgdb-to-gpkg
Version: 0.4.5
Summary: A lightweight Python package that converts Esri File GeoDataBases into OGC GeoPackages
Project-URL: Repository, https://github.com/philiporlando/fgdb_to_gpkg
Project-URL: Issues, https://github.com/philiporlando/fgdb_to_gpkg/issues
Author-email: Philip Orlando <phlp.orlando@gmail.com>, Brandon Istenes <bistenes@gmail.com>
License-File: LICENSE
Requires-Python: >=3.10
Requires-Dist: fiona>=1.10.1
Requires-Dist: geodatasets>=2024.8.0
Requires-Dist: geopandas==1.1.1
Requires-Dist: pyogrio>=0.11.1
Requires-Dist: pytest>=7.4.4
Requires-Dist: tqdm>=4.67.1
